PyEditor-0.2.1.dist-info/DESCRIPTION.rst
PyEditor-0.2.1.dist-info/METADATA
PyEditor-0.2.1.dist-info/RECORD
PyEditor-0.2.1.dist-info/WHEEL
PyEditor-0.2.1.dist-info/entry_points.txt
PyEditor-0.2.1.dist-info/metadata.json
PyEditor-0.2.1.dist-info/top_level.txt
pyeditor/__init__.py
pyeditor/__main__.py
pyeditor/config.py
pyeditor/constants.py
pyeditor/editor_window.py
pyeditor/example_scripts.py
pyeditor/minecraft_specials.py
pyeditor/python_files.py
pyeditor/script_list.py
pyeditor/version.py
pyeditor/tk_helpers/__init__.py
pyeditor/tk_helpers/mymultistatusbar.py
pyeditor/tk_helpers/scrolledlistbox.py
pyeditor/tk_helpers/tk_subprocess.py
pyeditor_tests/__init__.py
