Metadata-Version: 2.0
Name: PyEditor
Version: 0.2.1
Summary: Python Editor for beginners and Minecraft Fans
Home-page: https://github.com/PyEditor/PyEditor
Author: Jens Diemer
Author-email: PyEditor@jensdiemer.de
License: GPL v3+
Platform: UNKNOWN
Classifier: Development Status :: 2 - Pre-Alpha
Classifier: Intended Audience :: Developers
Classifier: License :: OSI Approved :: GNU General Public License v3 or later (GPLv3+)
Classifier: Operating System :: MacOS :: MacOS X
Classifier: Operating System :: Microsoft :: Windows
Classifier: Operating System :: POSIX
Classifier: Programming Language :: Python
Classifier: Programming Language :: Python :: 3
Classifier: Programming Language :: Python :: 3.4
Classifier: Programming Language :: Python :: 3.5
Classifier: Programming Language :: Python :: 3.6
Classifier: Topic :: Internet
Requires-Dist: psutil
